CyberGear/__init__.py
CyberGear/shell/__init__.py
CyberGear/shell/usage.py
CyberGear/src/temp.txt
PyCyberGear/__init__.py
PyCyberGear/shell/__init__.py
PyCyberGear/shell/usage.py
PyCyberGear/src/temp.txt
CyberGear-0.0.1.dist-info/LICENSE
CyberGear-0.0.1.dist-info/METADATA
CyberGear-0.0.1.dist-info/WHEEL
CyberGear-0.0.1.dist-info/entry_points.txt
CyberGear-0.0.1.dist-info/top_level.txt
CyberGear-0.0.1.dist-info/zip-safe
CyberGear-0.0.1.dist-info/RECORD
